asimplevectors/__init__.py
asimplevectors/client.py
asimplevectors/models.py
asimplevectors-0.2.2.1.dist-info/METADATA
asimplevectors-0.2.2.1.dist-info/WHEEL
asimplevectors-0.2.2.1.dist-info/top_level.txt
asimplevectors-0.2.2.1.dist-info/RECORD
