Metadata-Version: 2.1
Name: asimplevectors
Version: 0.2.2.1
Summary: Python client library for interacting with asimplevectors API.
Home-page: https://github.com/billionvectors/client_api.git
Author: billionvectors
Author-email: support@billionvectors.com
License: MIT
Classifier: Programming Language :: Python :: 3.8
Classifier: Programming Language :: Python :: 3.9
Classifier: License :: OSI Approved :: MIT License
Classifier: Operating System :: OS Independent
Requires-Python: >=3.8
Requires-Dist: aiofiles >=23.1.0
Requires-Dist: aiohttp >=3.8.5
Requires-Dist: httpx >=0.24.1
Requires-Dist: numpy >=1.21.0
Requires-Dist: pydantic >=2.1.1
Requires-Dist: requests-toolbelt >=0.10.1
Requires-Dist: requests >=2.25.1
